Metadata-Version: 2.4
Name: llama-index-vector-stores-tablestore
Version: 0.3.1
Summary: llama-index vector_stores tablestore integration
Author-email: "xunjian.sl" <xunjian.sl@alibaba-inc.com>
License-Expression: MIT
License-File: LICENSE
Requires-Python: <4.0,>=3.9
Requires-Dist: llama-index-core<0.15,>=0.13.0
Requires-Dist: tablestore>=6.1.0
